{
  "AL": "AL Altena (LÜD, ab 1975 LS, seit 1979 MK)",
  "ALS": "ALS Alsfeld, seit 1972 Vogelsbergkreis (VB)",
  "AR": "AR Arnsberg (MES, seit 1979 HSK)",
  "ASD": "ASD Aschendorf (Landkreis Aschendorf-Hümmling) (EL)",
  "BEI": "BEI Beilngries (EIH, seit 1979 EI)",
  "BEL": "BEL Belzig (PM)",
  "BG": "BG Bundesgrenzschutz (BP)",
  "BOG": "BOG Bogen (SR)",
  "BP": "BP (1956) Deutsche Bundespost",
  "BR": "BR Bruchsal (KA)",
  "BRI": "BRI Brilon (MES, seit 1979 HSK)",
  "BSB": "BSB Bersenbrück (OS)",
  "BU": "BU Burgdorf (H)",
  "BZA": "BZA Bergzabern (LD, seit 1979 SÜW)",
  "DB": "DB Deutsche Bundesbahn",
  "DS": "DS Donaueschingen (VS)",
  "DT": "DT Detmold, ab 1973 Lippe (LIP)",
  "EHI": "EHI Ehingen (Donau) (UL)",
  "EIH": "EIH kreisfreie Stadt Eichstätt und Landkreis Eichstätt (EI)",
  "ESA": "ESA Eisenach (WAK, seit 1998 auch EA)",
  "EUT": "EUT Eutin (OH)",
  "FAL": "FAL Fallingbostel, ab 1977 Soltau-Fallingbostel (SFA, seit 2011 HK)",
  "FH": "FH Frankfurt-Höchst (Main-Taunus-Kreis) (MTK)",
  "GEM": "GEM Gemünden am Main (KAR, seit 1979 MSP)",
  "GRS": "GRS Gransee (OHV)",
  "HÜN": "HÜN Hünfeld (FD)",
  "HUS": "HUS Husum (NF)",
  "HW": "HW Halle (Westfalen) (GT)",
  "HZ": "HZ (1991) Herzberg (EE)",
  "IS": ": IS kreisfreie Stadt Iserlohn und Kreis Iserlohn (LS, seit 1979 MK)",
  "JB": "JB Jüterbog (TF)",
  "JEV": "JEV Jever (Landkreis Friesland) (FRI)",
  "KAR": ": KAR Karlstadt, ab 1974 Main-Spessart (MSP)",
  "L": "L (1977) kreisfreie Stadt Lahn und Lahn-Dill-Kreis (GI/LDK/WZ)",
  "LAT": "LAT Lauterbach, ab 1972 Vogelsbergkreis (VB)",
  "LE": "LE Lemgo (DT, seit 1990 LIP)",
  "LIN": "LIN Lingen (EL)",
  "LK": "LK Lübbecke (MI)",
  "LOH": "LOH Lohr am Main (KAR, seit 1979 MSP)",
  "LS": "LS Lüdenscheid (Märkischer Kreis) (MK)",
  "LÜD": "LÜD kreisfreie Stadt Lüdenscheid, ab 1969 Kreis Lüdenscheid (LS, seit 1979 MK)",
  "LUK": "LUK Luckenwalde (TF)",
  "MAR": "MAR Marktheidenfeld (KAR, seit 1979 MSP)",
  "MEL": "MEL Melle (OS)",
  "MEP": "MEP Meppen (EL)",
  "MES": "MES Meschede, ab 1975 Hochsauerlandkreis (HSK)",
  "MT": "MT Montabaur Unterwesterwaldkreis, ab 1974 Westerwaldkreis (WW)",
  "MÜL": "MÜL Müllheim (Baden) (FR)",
  "MÜN": "MÜN Münsingen (RT)",
  "NEU": "NEU Neustadt im Schwarzwald (Landkreis Hochschwarzwald) (FR)",
  "NH": "NH (1956) kreisfreie Stadt Neustadt an der Haardt (Neustadt an der Weinstraße) und Landkreis Neustadt an der Haardt (Landkreis Neustadt an der Weinstraße) (NW)",
  "NIB": "NIB Niebüll (Kreis Südtondern) (NF)",
  "NRÜ": "NRÜ Neustadt am Rübenberge (H)",
  "NW": "NW (1956) Neuwied (NR)",
  "OLD": "OLD Oldenburg in Holstein (OH)",
  "OR": "OR Oranienburg (OHV)",
  "OTT": "OTT Otterndorf (Landkreis Land Hadeln) (CUX)",
  "OTW": "OTW Ottweiler (NK)",
  "OVP": "OVP Ostvorpommern (VG)",
  "PER": "PER Perleberg (PR)",
  "PK": "PK Pritzwalk (PR)",
  "ROH": "ROH Rotenburg in Hannover (ROW)",
  "RWL": "RWL Rheinland, Westfalen, Landesregierung und Landtag (Nordrhein-Westfalen, Landesregierung und Landtag) (NRW)",
  "RY": "RY kreisfreie Stadt Rheydt (MG)",
  "SÄK": "SÄK Säckingen (WT)",
  "SF": "SF Sonthofen, ab 1972 Oberallgäu (OA)",
  "SFA": "SFA Soltau-Fallingbostel (HK)",
  "SLG": "SLG Saulgau (SIG)",
  "SNH": "SNH Sinsheim (HD)",
  "SOL": "SOL Soltau (FAL, ab 1981 SFA, seit 2011 HK)",
  "SPR": "SPR Springe (H)",
  "ST": "ST (1956) Stade (STD)",
  "STH": "STH Stadthagen (Landkreis Schaumburg-Lippe) (SHG)",
  "STO": "STO Stockach (Baden) (KN)",
  "TÖN": "TÖN Tönning (Kreis Eiderstedt) (NF)",
  "TT": "TT Tettnang (FN)",
  "ÜB": "ÜB Überlingen (FN)",
  "UER": "UER Uecker-Randow (VG)",
  "VL": "VL Villingen (VS)",
  "VOF": "VOF Vilshofen (PA)",
  "WAR": "WAR Warburg (HX)",
  "WD": "WD Wiedenbrück (GT)",
  "WEB": "WEB Westerburg (Oberwesterwaldkreis) (MT, seit 1979 WW)",
  "WEG": "WEG Wegscheid (PA)",
  "WEM": "WEM Wesermünde (CUX)",
  "WG": "WG Wangen (RV)",
  "WTL": "WTL Wittlage (OS)",
  "ZS": ": ZS Zossen (TF)"
}